[
  {
    "timestamp": "2026-06-06T10:49:55.393554+00:00",
    "source": "Green Climate Fund",
    "title": "GCF Readiness Support for SAF Project Development in West Africa",
    "amount_usd": 2500000,
    "funding_type": "Grant",
    "url": "https://www.greenclimate.fund/project/readiness-saf-west-africa",
    "deadline": "2025-06-30",
    "eligibility": [
      "Nigeria",
      "Ghana",
      "Senegal"
    ],
    "focus_areas": [
      "SAF",
      "biofuels",
      "climate mitigation"
    ],
    "relevance_score": 83,
    "mode": "mock"
  },
  {
    "timestamp": "2026-06-05T11:28:50.218326+00:00",
    "source": "Climate Investment Funds",
    "title": "CIF Accelerating Coal Transition - Biofuels Alternative Track",
    "amount_usd": 15000000,
    "funding_type": "Concessional Loan",
    "url": "https://www.cif.org/act-biofuels",
    "deadline": "2025-08-15",
    "eligibility": [
      "CIF eligible countries"
    ],
    "focus_areas": [
      "just transition",
      "biofuels",
      "SAF"
    ],
    "relevance_score": 73,
    "mode": "mock"
  },
  {
    "timestamp": "2026-06-05T11:28:50.218292+00:00",
    "source": "Shell Foundation",
    "title": "Cassava-to-SAF Value Chain Development Grant",
    "amount_usd": 750000,
    "funding_type": "Grant",
    "url": "https://shellfoundation.org/cassava-saf",
    "deadline": "Rolling",
    "eligibility": [
      "Nigeria",
      "Tanzania",
      "Mozambique"
    ],
    "focus_areas": [
      "cassava",
      "value chain",
      "SAF"
    ],
    "relevance_score": 90,
    "mode": "mock"
  },
  {
    "timestamp": "2026-06-04T11:28:50.218319+00:00",
    "source": "Green Climate Fund",
    "title": "GCF Readiness Support for SAF Project Development in West Africa",
    "amount_usd": 2500000,
    "funding_type": "Grant",
    "url": "https://www.greenclimate.fund/project/readiness-saf-west-africa",
    "deadline": "2025-06-30",
    "eligibility": [
      "Nigeria",
      "Ghana",
      "Senegal"
    ],
    "focus_areas": [
      "SAF",
      "biofuels",
      "climate mitigation"
    ],
    "relevance_score": 79,
    "mode": "mock"
  },
  {
    "timestamp": "2026-06-03T12:19:03.703742+00:00",
    "source": "Shell Foundation",
    "title": "Cassava-to-SAF Value Chain Development Grant",
    "amount_usd": 750000,
    "funding_type": "Grant",
    "url": "https://shellfoundation.org/cassava-saf",
    "deadline": "Rolling",
    "eligibility": [
      "Nigeria",
      "Tanzania",
      "Mozambique"
    ],
    "focus_areas": [
      "cassava",
      "value chain",
      "SAF"
    ],
    "relevance_score": 84,
    "mode": "mock"
  },
  {
    "timestamp": "2026-06-03T10:19:19.467816+00:00",
    "source": "African Development Bank",
    "title": "AfDB SEFA Grant for Sustainable Aviation Feasibility Studies",
    "amount_usd": 1000000,
    "funding_type": "Technical Assistance",
    "url": "https://www.afdb.org/sefa-saf-feasibility",
    "deadline": "2025-04-15",
    "eligibility": [
      "African Union Member States"
    ],
    "focus_areas": [
      "feasibility study",
      "SAF",
      "aviation decarbonization"
    ],
    "relevance_score": 90,
    "mode": "mock"
  },
  {
    "timestamp": "2026-06-02T11:55:26.223408+00:00",
    "source": "Climate Investment Funds",
    "title": "CIF Accelerating Coal Transition - Biofuels Alternative Track",
    "amount_usd": 15000000,
    "funding_type": "Concessional Loan",
    "url": "https://www.cif.org/act-biofuels",
    "deadline": "2025-08-15",
    "eligibility": [
      "CIF eligible countries"
    ],
    "focus_areas": [
      "just transition",
      "biofuels",
      "SAF"
    ],
    "relevance_score": 72,
    "mode": "mock"
  },
  {
    "timestamp": "2026-06-02T11:55:26.223404+00:00",
    "source": "EU Global Gateway",
    "title": "Team Europe Initiative: African Green Hydrogen and SAF Corridor",
    "amount_usd": 50000000,
    "funding_type": "Blended Finance",
    "url": "https://ec.europa.eu/global-gateway/africa-saf-corridor",
    "deadline": "2025-09-01",
    "eligibility": [
      "ECOWAS countries"
    ],
    "focus_areas": [
      "green hydrogen",
      "SAF",
      "infrastructure"
    ],
    "relevance_score": 85,
    "mode": "mock"
  },
  {
    "timestamp": "2026-06-01T12:27:26.720855+00:00",
    "source": "Climate Investment Funds",
    "title": "CIF Accelerating Coal Transition - Biofuels Alternative Track",
    "amount_usd": 15000000,
    "funding_type": "Concessional Loan",
    "url": "https://www.cif.org/act-biofuels",
    "deadline": "2025-08-15",
    "eligibility": [
      "CIF eligible countries"
    ],
    "focus_areas": [
      "just transition",
      "biofuels",
      "SAF"
    ],
    "relevance_score": 85,
    "mode": "mock"
  },
  {
    "timestamp": "2026-06-01T10:19:19.467844+00:00",
    "source": "USAID Power Africa",
    "title": "Off-Grid Bioenergy for SAF Feedstock Processing",
    "amount_usd": 5000000,
    "funding_type": "Grant",
    "url": "https://www.usaid.gov/powerafrica/bioenergy-saf",
    "deadline": "2025-05-20",
    "eligibility": [
      "Nigeria",
      "Kenya",
      "South Africa"
    ],
    "focus_areas": [
      "bioenergy",
      "feedstock processing",
      "rural electrification"
    ],
    "relevance_score": 83,
    "mode": "mock"
  },
  {
    "timestamp": "2026-05-31T09:51:11.689702+00:00",
    "source": "Green Climate Fund",
    "title": "GCF Readiness Support for SAF Project Development in West Africa",
    "amount_usd": 2500000,
    "funding_type": "Grant",
    "url": "https://www.greenclimate.fund/project/readiness-saf-west-africa",
    "deadline": "2025-06-30",
    "eligibility": [
      "Nigeria",
      "Ghana",
      "Senegal"
    ],
    "focus_areas": [
      "SAF",
      "biofuels",
      "climate mitigation"
    ],
    "relevance_score": 83,
    "mode": "mock"
  },
  {
    "timestamp": "2026-05-30T10:52:35.753521+00:00",
    "source": "Climate Investment Funds",
    "title": "CIF Accelerating Coal Transition - Biofuels Alternative Track",
    "amount_usd": 15000000,
    "funding_type": "Concessional Loan",
    "url": "https://www.cif.org/act-biofuels",
    "deadline": "2025-08-15",
    "eligibility": [
      "CIF eligible countries"
    ],
    "focus_areas": [
      "just transition",
      "biofuels",
      "SAF"
    ],
    "relevance_score": 94,
    "mode": "mock"
  },
  {
    "timestamp": "2026-05-30T10:05:13.724353+00:00",
    "source": "Climate Investment Funds",
    "title": "CIF Accelerating Coal Transition - Biofuels Alternative Track",
    "amount_usd": 15000000,
    "funding_type": "Concessional Loan",
    "url": "https://www.cif.org/act-biofuels",
    "deadline": "2025-08-15",
    "eligibility": [
      "CIF eligible countries"
    ],
    "focus_areas": [
      "just transition",
      "biofuels",
      "SAF"
    ],
    "relevance_score": 70,
    "mode": "mock"
  },
  {
    "timestamp": "2026-05-30T09:48:19.604764+00:00",
    "source": "Shell Foundation",
    "title": "Cassava-to-SAF Value Chain Development Grant",
    "amount_usd": 750000,
    "funding_type": "Grant",
    "url": "https://shellfoundation.org/cassava-saf",
    "deadline": "Rolling",
    "eligibility": [
      "Nigeria",
      "Tanzania",
      "Mozambique"
    ],
    "focus_areas": [
      "cassava",
      "value chain",
      "SAF"
    ],
    "relevance_score": 85,
    "mode": "mock"
  },
  {
    "timestamp": "2026-05-29T10:49:55.393541+00:00",
    "source": "Shell Foundation",
    "title": "Cassava-to-SAF Value Chain Development Grant",
    "amount_usd": 750000,
    "funding_type": "Grant",
    "url": "https://shellfoundation.org/cassava-saf",
    "deadline": "Rolling",
    "eligibility": [
      "Nigeria",
      "Tanzania",
      "Mozambique"
    ],
    "focus_areas": [
      "cassava",
      "value chain",
      "SAF"
    ],
    "relevance_score": 91,
    "mode": "mock"
  },
  {
    "timestamp": "2026-05-28T12:27:26.720825+00:00",
    "source": "Green Climate Fund",
    "title": "GCF Readiness Support for SAF Project Development in West Africa",
    "amount_usd": 2500000,
    "funding_type": "Grant",
    "url": "https://www.greenclimate.fund/project/readiness-saf-west-africa",
    "deadline": "2025-06-30",
    "eligibility": [
      "Nigeria",
      "Ghana",
      "Senegal"
    ],
    "focus_areas": [
      "SAF",
      "biofuels",
      "climate mitigation"
    ],
    "relevance_score": 73,
    "mode": "mock"
  },
  {
    "timestamp": "2026-05-28T11:16:52.676640+00:00",
    "source": "Shell Foundation",
    "title": "Cassava-to-SAF Value Chain Development Grant",
    "amount_usd": 750000,
    "funding_type": "Grant",
    "url": "https://shellfoundation.org/cassava-saf",
    "deadline": "Rolling",
    "eligibility": [
      "Nigeria",
      "Tanzania",
      "Mozambique"
    ],
    "focus_areas": [
      "cassava",
      "value chain",
      "SAF"
    ],
    "relevance_score": 88,
    "mode": "mock"
  },
  {
    "timestamp": "2026-05-28T11:16:28.261299+00:00",
    "source": "Shell Foundation",
    "title": "Cassava-to-SAF Value Chain Development Grant",
    "amount_usd": 750000,
    "funding_type": "Grant",
    "url": "https://shellfoundation.org/cassava-saf",
    "deadline": "Rolling",
    "eligibility": [
      "Nigeria",
      "Tanzania",
      "Mozambique"
    ],
    "focus_areas": [
      "cassava",
      "value chain",
      "SAF"
    ],
    "relevance_score": 73,
    "mode": "mock"
  },
  {
    "timestamp": "2026-05-28T11:16:28.261264+00:00",
    "source": "African Development Bank",
    "title": "AfDB SEFA Grant for Sustainable Aviation Feasibility Studies",
    "amount_usd": 1000000,
    "funding_type": "Technical Assistance",
    "url": "https://www.afdb.org/sefa-saf-feasibility",
    "deadline": "2025-04-15",
    "eligibility": [
      "African Union Member States"
    ],
    "focus_areas": [
      "feasibility study",
      "SAF",
      "aviation decarbonization"
    ],
    "relevance_score": 83,
    "mode": "mock"
  },
  {
    "timestamp": "2026-05-28T10:52:35.753527+00:00",
    "source": "EU Global Gateway",
    "title": "Team Europe Initiative: African Green Hydrogen and SAF Corridor",
    "amount_usd": 50000000,
    "funding_type": "Blended Finance",
    "url": "https://ec.europa.eu/global-gateway/africa-saf-corridor",
    "deadline": "2025-09-01",
    "eligibility": [
      "ECOWAS countries"
    ],
    "focus_areas": [
      "green hydrogen",
      "SAF",
      "infrastructure"
    ],
    "relevance_score": 95,
    "mode": "mock"
  },
  {
    "timestamp": "2026-05-27T13:24:30.841757+00:00",
    "source": "African Development Bank",
    "title": "AfDB SEFA Grant for Sustainable Aviation Feasibility Studies",
    "amount_usd": 1000000,
    "funding_type": "Technical Assistance",
    "url": "https://www.afdb.org/sefa-saf-feasibility",
    "deadline": "2025-04-15",
    "eligibility": [
      "African Union Member States"
    ],
    "focus_areas": [
      "feasibility study",
      "SAF",
      "aviation decarbonization"
    ],
    "relevance_score": 83,
    "mode": "mock"
  },
  {
    "timestamp": "2026-05-27T12:19:03.703735+00:00",
    "source": "African Development Bank",
    "title": "AfDB SEFA Grant for Sustainable Aviation Feasibility Studies",
    "amount_usd": 1000000,
    "funding_type": "Technical Assistance",
    "url": "https://www.afdb.org/sefa-saf-feasibility",
    "deadline": "2025-04-15",
    "eligibility": [
      "African Union Member States"
    ],
    "focus_areas": [
      "feasibility study",
      "SAF",
      "aviation decarbonization"
    ],
    "relevance_score": 92,
    "mode": "mock"
  },
  {
    "timestamp": "2026-05-27T12:19:03.703712+00:00",
    "source": "Green Climate Fund",
    "title": "GCF Readiness Support for SAF Project Development in West Africa",
    "amount_usd": 2500000,
    "funding_type": "Grant",
    "url": "https://www.greenclimate.fund/project/readiness-saf-west-africa",
    "deadline": "2025-06-30",
    "eligibility": [
      "Nigeria",
      "Ghana",
      "Senegal"
    ],
    "focus_areas": [
      "SAF",
      "biofuels",
      "climate mitigation"
    ],
    "relevance_score": 78,
    "mode": "mock"
  },
  {
    "timestamp": "2026-05-27T11:26:49.703976+00:00",
    "source": "Climate Investment Funds",
    "title": "CIF Accelerating Coal Transition - Biofuels Alternative Track",
    "amount_usd": 15000000,
    "funding_type": "Concessional Loan",
    "url": "https://www.cif.org/act-biofuels",
    "deadline": "2025-08-15",
    "eligibility": [
      "CIF eligible countries"
    ],
    "focus_areas": [
      "just transition",
      "biofuels",
      "SAF"
    ],
    "relevance_score": 89,
    "mode": "mock"
  },
  {
    "timestamp": "2026-05-27T11:16:28.261291+00:00",
    "source": "USAID Power Africa",
    "title": "Off-Grid Bioenergy for SAF Feedstock Processing",
    "amount_usd": 5000000,
    "funding_type": "Grant",
    "url": "https://www.usaid.gov/powerafrica/bioenergy-saf",
    "deadline": "2025-05-20",
    "eligibility": [
      "Nigeria",
      "Kenya",
      "South Africa"
    ],
    "focus_areas": [
      "bioenergy",
      "feedstock processing",
      "rural electrification"
    ],
    "relevance_score": 90,
    "mode": "mock"
  },
  {
    "timestamp": "2026-05-27T10:49:55.393558+00:00",
    "source": "EU Global Gateway",
    "title": "Team Europe Initiative: African Green Hydrogen and SAF Corridor",
    "amount_usd": 50000000,
    "funding_type": "Blended Finance",
    "url": "https://ec.europa.eu/global-gateway/africa-saf-corridor",
    "deadline": "2025-09-01",
    "eligibility": [
      "ECOWAS countries"
    ],
    "focus_areas": [
      "green hydrogen",
      "SAF",
      "infrastructure"
    ],
    "relevance_score": 99,
    "mode": "mock"
  },
  {
    "timestamp": "2026-05-27T10:49:55.393549+00:00",
    "source": "Climate Investment Funds",
    "title": "CIF Accelerating Coal Transition - Biofuels Alternative Track",
    "amount_usd": 15000000,
    "funding_type": "Concessional Loan",
    "url": "https://www.cif.org/act-biofuels",
    "deadline": "2025-08-15",
    "eligibility": [
      "CIF eligible countries"
    ],
    "focus_areas": [
      "just transition",
      "biofuels",
      "SAF"
    ],
    "relevance_score": 81,
    "mode": "mock"
  },
  {
    "timestamp": "2026-05-27T10:49:55.393495+00:00",
    "source": "USAID Power Africa",
    "title": "Off-Grid Bioenergy for SAF Feedstock Processing",
    "amount_usd": 5000000,
    "funding_type": "Grant",
    "url": "https://www.usaid.gov/powerafrica/bioenergy-saf",
    "deadline": "2025-05-20",
    "eligibility": [
      "Nigeria",
      "Kenya",
      "South Africa"
    ],
    "focus_areas": [
      "bioenergy",
      "feedstock processing",
      "rural electrification"
    ],
    "relevance_score": 83,
    "mode": "mock"
  },
  {
    "timestamp": "2026-05-27T10:05:13.724330+00:00",
    "source": "EU Global Gateway",
    "title": "Team Europe Initiative: African Green Hydrogen and SAF Corridor",
    "amount_usd": 50000000,
    "funding_type": "Blended Finance",
    "url": "https://ec.europa.eu/global-gateway/africa-saf-corridor",
    "deadline": "2025-09-01",
    "eligibility": [
      "ECOWAS countries"
    ],
    "focus_areas": [
      "green hydrogen",
      "SAF",
      "infrastructure"
    ],
    "relevance_score": 76,
    "mode": "mock"
  },
  {
    "timestamp": "2026-05-27T09:51:11.689680+00:00",
    "source": "IFC",
    "title": "IFC Upstream: Early-Stage SAF Project Preparation Facility",
    "amount_usd": 3000000,
    "funding_type": "Technical Assistance",
    "url": "https://www.ifc.org/upstream-saf",
    "deadline": "2025-07-01",
    "eligibility": [
      "IDA countries"
    ],
    "focus_areas": [
      "project preparation",
      "SAF",
      "bankability"
    ],
    "relevance_score": 88,
    "mode": "mock"
  }
]