[
  {
    "timestamp": "2026-05-05T10:06:43.438784+00:00",
    "source": "Argonne National Lab",
    "title": "GREET Model Update: Revised LCA for Tropical Feedstocks",
    "pathway": "ETJ",
    "pathway_full": "Ethanol-to-Jet",
    "update_type": "Research",
    "url": "https://greet.es.anl.gov/tropical-feedstocks",
    "significance": "Improved carbon intensity calculations for cassava and sugarcane",
    "impact_score": 75,
    "mode": "mock"
  },
  {
    "timestamp": "2026-05-02T09:49:55.584404+00:00",
    "source": "ICAO CORSIA",
    "title": "CORSIA Eligible Fuels: New Cassava Ethanol Pathway Approved",
    "pathway": "ETJ",
    "pathway_full": "Ethanol-to-Jet",
    "update_type": "Certification",
    "url": "https://www.icao.int/corsia/eligible-fuels-cassava",
    "significance": "Opens pathway for African cassava-based SAF",
    "impact_score": 97,
    "mode": "mock"
  },
  {
    "timestamp": "2026-04-30T10:04:02.062139+00:00",
    "source": "LanzaJet",
    "title": "LanzaJet Georgia Plant Achieves First Commercial ATJ Production",
    "pathway": "AtJ",
    "pathway_full": "Alcohol-to-Jet",
    "update_type": "Commercial Milestone",
    "url": "https://www.lanzajet.com/georgia-commercial",
    "significance": "First commercial-scale ATJ facility in the Americas",
    "impact_score": 92,
    "mode": "mock"
  },
  {
    "timestamp": "2026-04-30T09:56:03.914231+00:00",
    "source": "ICAO CORSIA",
    "title": "CORSIA Eligible Fuels: New Cassava Ethanol Pathway Approved",
    "pathway": "ETJ",
    "pathway_full": "Ethanol-to-Jet",
    "update_type": "Certification",
    "url": "https://www.icao.int/corsia/eligible-fuels-cassava",
    "significance": "Opens pathway for African cassava-based SAF",
    "impact_score": 97,
    "mode": "mock"
  },
  {
    "timestamp": "2026-04-29T09:24:03.986309+00:00",
    "source": "LanzaJet",
    "title": "LanzaJet Georgia Plant Achieves First Commercial ATJ Production",
    "pathway": "AtJ",
    "pathway_full": "Alcohol-to-Jet",
    "update_type": "Commercial Milestone",
    "url": "https://www.lanzajet.com/georgia-commercial",
    "significance": "First commercial-scale ATJ facility in the Americas",
    "impact_score": 92,
    "mode": "mock"
  },
  {
    "timestamp": "2026-04-28T09:49:55.584369+00:00",
    "source": "RSB",
    "title": "Roundtable on Sustainable Biomaterials: New African Certification Scheme",
    "pathway": "Multiple",
    "pathway_full": "Multiple",
    "update_type": "Certification",
    "url": "https://rsb.org/africa-certification",
    "significance": "Simplified sustainability certification for African producers",
    "impact_score": 82,
    "mode": "mock"
  },
  {
    "timestamp": "2026-04-27T10:11:55.049001+00:00",
    "source": "Neste",
    "title": "Neste Singapore Expansion: 1.3M Tonnes SAF Capacity by 2026",
    "pathway": "HEFA",
    "pathway_full": "Hydroprocessed Esters and Fatty Acids",
    "update_type": "Capacity Expansion",
    "url": "https://www.neste.com/singapore-expansion",
    "significance": "Largest SAF production facility globally",
    "impact_score": 88,
    "mode": "mock"
  },
  {
    "timestamp": "2026-04-27T09:24:03.986301+00:00",
    "source": "Argonne National Lab",
    "title": "GREET Model Update: Revised LCA for Tropical Feedstocks",
    "pathway": "ETJ",
    "pathway_full": "Ethanol-to-Jet",
    "update_type": "Research",
    "url": "https://greet.es.anl.gov/tropical-feedstocks",
    "significance": "Improved carbon intensity calculations for cassava and sugarcane",
    "impact_score": 75,
    "mode": "mock"
  },
  {
    "timestamp": "2026-04-25T10:06:43.438773+00:00",
    "source": "LanzaJet",
    "title": "LanzaJet Georgia Plant Achieves First Commercial ATJ Production",
    "pathway": "AtJ",
    "pathway_full": "Alcohol-to-Jet",
    "update_type": "Commercial Milestone",
    "url": "https://www.lanzajet.com/georgia-commercial",
    "significance": "First commercial-scale ATJ facility in the Americas",
    "impact_score": 92,
    "mode": "mock"
  },
  {
    "timestamp": "2026-04-25T10:06:43.438746+00:00",
    "source": "ASTM International",
    "title": "ASTM D7566 Annex 7 Updated: Increased ETJ Blend Limit to 50%",
    "pathway": "ETJ",
    "pathway_full": "Ethanol-to-Jet",
    "update_type": "Certification",
    "url": "https://www.astm.org/d7566-annex7-update",
    "significance": "Major regulatory milestone enabling higher ETJ blending",
    "impact_score": 95,
    "mode": "mock"
  },
  {
    "timestamp": "2026-04-24T10:04:02.062178+00:00",
    "source": "Argonne National Lab",
    "title": "GREET Model Update: Revised LCA for Tropical Feedstocks",
    "pathway": "ETJ",
    "pathway_full": "Ethanol-to-Jet",
    "update_type": "Research",
    "url": "https://greet.es.anl.gov/tropical-feedstocks",
    "significance": "Improved carbon intensity calculations for cassava and sugarcane",
    "impact_score": 75,
    "mode": "mock"
  },
  {
    "timestamp": "2026-04-24T09:55:08.304792+00:00",
    "source": "ICAO CORSIA",
    "title": "CORSIA Eligible Fuels: New Cassava Ethanol Pathway Approved",
    "pathway": "ETJ",
    "pathway_full": "Ethanol-to-Jet",
    "update_type": "Certification",
    "url": "https://www.icao.int/corsia/eligible-fuels-cassava",
    "significance": "Opens pathway for African cassava-based SAF",
    "impact_score": 97,
    "mode": "mock"
  },
  {
    "timestamp": "2026-04-24T09:49:55.584392+00:00",
    "source": "ASTM International",
    "title": "ASTM D7566 Annex 7 Updated: Increased ETJ Blend Limit to 50%",
    "pathway": "ETJ",
    "pathway_full": "Ethanol-to-Jet",
    "update_type": "Certification",
    "url": "https://www.astm.org/d7566-annex7-update",
    "significance": "Major regulatory milestone enabling higher ETJ blending",
    "impact_score": 95,
    "mode": "mock"
  },
  {
    "timestamp": "2026-04-24T09:10:51.459729+00:00",
    "source": "ICAO CORSIA",
    "title": "CORSIA Eligible Fuels: New Cassava Ethanol Pathway Approved",
    "pathway": "ETJ",
    "pathway_full": "Ethanol-to-Jet",
    "update_type": "Certification",
    "url": "https://www.icao.int/corsia/eligible-fuels-cassava",
    "significance": "Opens pathway for African cassava-based SAF",
    "impact_score": 97,
    "mode": "mock"
  },
  {
    "timestamp": "2026-04-24T08:39:28.125577+00:00",
    "source": "RSB",
    "title": "Roundtable on Sustainable Biomaterials: New African Certification Scheme",
    "pathway": "Multiple",
    "pathway_full": "Multiple",
    "update_type": "Certification",
    "url": "https://rsb.org/africa-certification",
    "significance": "Simplified sustainability certification for African producers",
    "impact_score": 82,
    "mode": "mock"
  },
  {
    "timestamp": "2026-04-24T08:39:28.125553+00:00",
    "source": "ICAO CORSIA",
    "title": "CORSIA Eligible Fuels: New Cassava Ethanol Pathway Approved",
    "pathway": "ETJ",
    "pathway_full": "Ethanol-to-Jet",
    "update_type": "Certification",
    "url": "https://www.icao.int/corsia/eligible-fuels-cassava",
    "significance": "Opens pathway for African cassava-based SAF",
    "impact_score": 97,
    "mode": "mock"
  },
  {
    "timestamp": "2026-04-23T08:47:37.781202+00:00",
    "source": "Gevo",
    "title": "Gevo Net-Zero 1 Project Secures Final Investment Decision",
    "pathway": "AtJ",
    "pathway_full": "Alcohol-to-Jet",
    "update_type": "Investment",
    "url": "https://gevo.com/net-zero-1-fid",
    "significance": "Major AtJ project advancement in the US",
    "impact_score": 85,
    "mode": "mock"
  },
  {
    "timestamp": "2026-04-22T10:11:55.048976+00:00",
    "source": "RSB",
    "title": "Roundtable on Sustainable Biomaterials: New African Certification Scheme",
    "pathway": "Multiple",
    "pathway_full": "Multiple",
    "update_type": "Certification",
    "url": "https://rsb.org/africa-certification",
    "significance": "Simplified sustainability certification for African producers",
    "impact_score": 82,
    "mode": "mock"
  },
  {
    "timestamp": "2026-04-22T10:03:45.675590+00:00",
    "source": "LanzaJet",
    "title": "LanzaJet Georgia Plant Achieves First Commercial ATJ Production",
    "pathway": "AtJ",
    "pathway_full": "Alcohol-to-Jet",
    "update_type": "Commercial Milestone",
    "url": "https://www.lanzajet.com/georgia-commercial",
    "significance": "First commercial-scale ATJ facility in the Americas",
    "impact_score": 92,
    "mode": "mock"
  },
  {
    "timestamp": "2026-04-22T09:49:55.584399+00:00",
    "source": "World Energy",
    "title": "World Energy Achieves 100% SAF Production at Paramount Facility",
    "pathway": "HEFA",
    "pathway_full": "Hydroprocessed Esters and Fatty Acids",
    "update_type": "Commercial Milestone",
    "url": "https://www.worldenergy.net/paramount-100-saf",
    "significance": "First facility producing neat SAF at commercial scale",
    "impact_score": 90,
    "mode": "mock"
  },
  {
    "timestamp": "2026-04-22T09:24:03.986279+00:00",
    "source": "ICAO CORSIA",
    "title": "CORSIA Eligible Fuels: New Cassava Ethanol Pathway Approved",
    "pathway": "ETJ",
    "pathway_full": "Ethanol-to-Jet",
    "update_type": "Certification",
    "url": "https://www.icao.int/corsia/eligible-fuels-cassava",
    "significance": "Opens pathway for African cassava-based SAF",
    "impact_score": 97,
    "mode": "mock"
  },
  {
    "timestamp": "2026-04-22T09:09:55.510086+00:00",
    "source": "Argonne National Lab",
    "title": "GREET Model Update: Revised LCA for Tropical Feedstocks",
    "pathway": "ETJ",
    "pathway_full": "Ethanol-to-Jet",
    "update_type": "Research",
    "url": "https://greet.es.anl.gov/tropical-feedstocks",
    "significance": "Improved carbon intensity calculations for cassava and sugarcane",
    "impact_score": 75,
    "mode": "mock"
  },
  {
    "timestamp": "2026-04-21T10:06:43.438780+00:00",
    "source": "Neste",
    "title": "Neste Singapore Expansion: 1.3M Tonnes SAF Capacity by 2026",
    "pathway": "HEFA",
    "pathway_full": "Hydroprocessed Esters and Fatty Acids",
    "update_type": "Capacity Expansion",
    "url": "https://www.neste.com/singapore-expansion",
    "significance": "Largest SAF production facility globally",
    "impact_score": 88,
    "mode": "mock"
  },
  {
    "timestamp": "2026-04-20T10:03:09.567560+00:00",
    "source": "LanzaJet",
    "title": "LanzaJet Georgia Plant Achieves First Commercial ATJ Production",
    "pathway": "AtJ",
    "pathway_full": "Alcohol-to-Jet",
    "update_type": "Commercial Milestone",
    "url": "https://www.lanzajet.com/georgia-commercial",
    "significance": "First commercial-scale ATJ facility in the Americas",
    "impact_score": 92,
    "mode": "mock"
  },
  {
    "timestamp": "2026-04-20T09:56:03.914254+00:00",
    "source": "RSB",
    "title": "Roundtable on Sustainable Biomaterials: New African Certification Scheme",
    "pathway": "Multiple",
    "pathway_full": "Multiple",
    "update_type": "Certification",
    "url": "https://rsb.org/africa-certification",
    "significance": "Simplified sustainability certification for African producers",
    "impact_score": 82,
    "mode": "mock"
  },
  {
    "timestamp": "2026-04-20T09:55:08.304815+00:00",
    "source": "Neste",
    "title": "Neste Singapore Expansion: 1.3M Tonnes SAF Capacity by 2026",
    "pathway": "HEFA",
    "pathway_full": "Hydroprocessed Esters and Fatty Acids",
    "update_type": "Capacity Expansion",
    "url": "https://www.neste.com/singapore-expansion",
    "significance": "Largest SAF production facility globally",
    "impact_score": 88,
    "mode": "mock"
  },
  {
    "timestamp": "2026-04-19T09:56:03.914266+00:00",
    "source": "World Energy",
    "title": "World Energy Achieves 100% SAF Production at Paramount Facility",
    "pathway": "HEFA",
    "pathway_full": "Hydroprocessed Esters and Fatty Acids",
    "update_type": "Commercial Milestone",
    "url": "https://www.worldenergy.net/paramount-100-saf",
    "significance": "First facility producing neat SAF at commercial scale",
    "impact_score": 90,
    "mode": "mock"
  },
  {
    "timestamp": "2026-04-19T09:15:38.930325+00:00",
    "source": "World Energy",
    "title": "World Energy Achieves 100% SAF Production at Paramount Facility",
    "pathway": "HEFA",
    "pathway_full": "Hydroprocessed Esters and Fatty Acids",
    "update_type": "Commercial Milestone",
    "url": "https://www.worldenergy.net/paramount-100-saf",
    "significance": "First facility producing neat SAF at commercial scale",
    "impact_score": 90,
    "mode": "mock"
  },
  {
    "timestamp": "2026-04-19T09:10:51.459750+00:00",
    "source": "Argonne National Lab",
    "title": "GREET Model Update: Revised LCA for Tropical Feedstocks",
    "pathway": "ETJ",
    "pathway_full": "Ethanol-to-Jet",
    "update_type": "Research",
    "url": "https://greet.es.anl.gov/tropical-feedstocks",
    "significance": "Improved carbon intensity calculations for cassava and sugarcane",
    "impact_score": 75,
    "mode": "mock"
  },
  {
    "timestamp": "2026-04-18T10:03:09.567594+00:00",
    "source": "World Energy",
    "title": "World Energy Achieves 100% SAF Production at Paramount Facility",
    "pathway": "HEFA",
    "pathway_full": "Hydroprocessed Esters and Fatty Acids",
    "update_type": "Commercial Milestone",
    "url": "https://www.worldenergy.net/paramount-100-saf",
    "significance": "First facility producing neat SAF at commercial scale",
    "impact_score": 90,
    "mode": "mock"
  },
  {
    "timestamp": "2026-04-18T09:56:03.914261+00:00",
    "source": "Argonne National Lab",
    "title": "GREET Model Update: Revised LCA for Tropical Feedstocks",
    "pathway": "ETJ",
    "pathway_full": "Ethanol-to-Jet",
    "update_type": "Research",
    "url": "https://greet.es.anl.gov/tropical-feedstocks",
    "significance": "Improved carbon intensity calculations for cassava and sugarcane",
    "impact_score": 75,
    "mode": "mock"
  },
  {
    "timestamp": "2026-04-18T08:35:43.076364+00:00",
    "source": "RSB",
    "title": "Roundtable on Sustainable Biomaterials: New African Certification Scheme",
    "pathway": "Multiple",
    "pathway_full": "Multiple",
    "update_type": "Certification",
    "url": "https://rsb.org/africa-certification",
    "significance": "Simplified sustainability certification for African producers",
    "impact_score": 82,
    "mode": "mock"
  },
  {
    "timestamp": "2026-04-17T10:03:45.675552+00:00",
    "source": "ICAO CORSIA",
    "title": "CORSIA Eligible Fuels: New Cassava Ethanol Pathway Approved",
    "pathway": "ETJ",
    "pathway_full": "Ethanol-to-Jet",
    "update_type": "Certification",
    "url": "https://www.icao.int/corsia/eligible-fuels-cassava",
    "significance": "Opens pathway for African cassava-based SAF",
    "impact_score": 97,
    "mode": "mock"
  },
  {
    "timestamp": "2026-04-17T09:09:55.510117+00:00",
    "source": "ASTM International",
    "title": "ASTM D7566 Annex 7 Updated: Increased ETJ Blend Limit to 50%",
    "pathway": "ETJ",
    "pathway_full": "Ethanol-to-Jet",
    "update_type": "Certification",
    "url": "https://www.astm.org/d7566-annex7-update",
    "significance": "Major regulatory milestone enabling higher ETJ blending",
    "impact_score": 95,
    "mode": "mock"
  },
  {
    "timestamp": "2026-04-16T10:04:02.062173+00:00",
    "source": "World Energy",
    "title": "World Energy Achieves 100% SAF Production at Paramount Facility",
    "pathway": "HEFA",
    "pathway_full": "Hydroprocessed Esters and Fatty Acids",
    "update_type": "Commercial Milestone",
    "url": "https://www.worldenergy.net/paramount-100-saf",
    "significance": "First facility producing neat SAF at commercial scale",
    "impact_score": 90,
    "mode": "mock"
  },
  {
    "timestamp": "2026-04-16T10:04:02.062165+00:00",
    "source": "ASTM International",
    "title": "ASTM D7566 Annex 7 Updated: Increased ETJ Blend Limit to 50%",
    "pathway": "ETJ",
    "pathway_full": "Ethanol-to-Jet",
    "update_type": "Certification",
    "url": "https://www.astm.org/d7566-annex7-update",
    "significance": "Major regulatory milestone enabling higher ETJ blending",
    "impact_score": 95,
    "mode": "mock"
  },
  {
    "timestamp": "2026-04-16T09:16:29.325719+00:00",
    "source": "LanzaJet",
    "title": "LanzaJet Georgia Plant Achieves First Commercial ATJ Production",
    "pathway": "AtJ",
    "pathway_full": "Alcohol-to-Jet",
    "update_type": "Commercial Milestone",
    "url": "https://www.lanzajet.com/georgia-commercial",
    "significance": "First commercial-scale ATJ facility in the Americas",
    "impact_score": 92,
    "mode": "mock"
  },
  {
    "timestamp": "2026-04-16T09:06:36.923760+00:00",
    "source": "Gevo",
    "title": "Gevo Net-Zero 1 Project Secures Final Investment Decision",
    "pathway": "AtJ",
    "pathway_full": "Alcohol-to-Jet",
    "update_type": "Investment",
    "url": "https://gevo.com/net-zero-1-fid",
    "significance": "Major AtJ project advancement in the US",
    "impact_score": 85,
    "mode": "mock"
  },
  {
    "timestamp": "2026-04-16T09:06:36.923729+00:00",
    "source": "ICAO CORSIA",
    "title": "CORSIA Eligible Fuels: New Cassava Ethanol Pathway Approved",
    "pathway": "ETJ",
    "pathway_full": "Ethanol-to-Jet",
    "update_type": "Certification",
    "url": "https://www.icao.int/corsia/eligible-fuels-cassava",
    "significance": "Opens pathway for African cassava-based SAF",
    "impact_score": 97,
    "mode": "mock"
  },
  {
    "timestamp": "2026-04-15T10:03:45.675585+00:00",
    "source": "RSB",
    "title": "Roundtable on Sustainable Biomaterials: New African Certification Scheme",
    "pathway": "Multiple",
    "pathway_full": "Multiple",
    "update_type": "Certification",
    "url": "https://rsb.org/africa-certification",
    "significance": "Simplified sustainability certification for African producers",
    "impact_score": 82,
    "mode": "mock"
  }
]